{"city_id":5693,"id":"cartagena-colombia","latitude":"10.386699","longitude":"-75.505683","name":"Cartagena, Colombia","type":"landing_point","cables":[{"cable_id":1078,"id":"arcos","name":"ARCOS"},{"cable_id":1924,"id":"aurora","name":"AURORA"},{"cable_id":1686,"id":"america-movil-submarine-cable-system-1-amx-1","name":"America Movil Submarine Cable System-1 (AMX-1)"},{"cable_id":1554,"id":"colombia-florida-subsea-fiber-cfx-1","name":"Colombia-Florida Subsea Fiber (CFX-1)"},{"cable_id":1913,"id":"deep-blue-cable","name":"Deep Blue Cable"},{"cable_id":1727,"id":"pacific-caribbean-cable-system-pccs","name":"Pacific Caribbean Cable System (PCCS)"}]}
