{"city_id":3214,"id":"catania-italy","latitude":"37.511588","longitude":"15.067443","name":"Catania, Italy","type":"landing_point","cables":[{"cable_id":1536,"id":"imewe","name":"IMEWE"},{"cable_id":1301,"id":"italy-malta","name":"Italy-Malta"},{"cable_id":1185,"id":"mednautilus-submarine-system","name":"MedNautilus Submarine System"},{"cable_id":1559,"id":"seamewe-5","name":"SeaMeWe-5"},{"cable_id":1249,"id":"vodafone-malta-sicily-cable-system-vmscs","name":"Vodafone Malta-Sicily Cable System (VMSCS)"}]}
